osmocom/__init__.py
osmocom/construct.py
osmocom/gsmtap.py
osmocom/tlv.py
osmocom/utils.py
osmocom/gsup/__init__.py
osmocom/gsup/message.py
pyosmocom-0.0.11.dist-info/licenses/COPYING
pyosmocom-0.0.11.dist-info/METADATA
pyosmocom-0.0.11.dist-info/WHEEL
pyosmocom-0.0.11.dist-info/top_level.txt
pyosmocom-0.0.11.dist-info/RECORD
