Metadata-Version: 2.4
Name: pyosmocom
Version: 0.0.11
Summary: Python implementation of core osmocom utilities / protocols
Maintainer-email: openbsc@lists.osmocom.org
License-Expression: GPL-2.0-or-later
Project-URL: Homepage, https://osmocom.org/projects/pyosmocom/wiki
Project-URL: Repository, https://gitea.osmocom.org/osmocom/pyosmocom
Project-URL: Bug Tracker, https://osmocom.org/projects/pyosmocom/issues
Keywords: telecom,gsm,3gpp,cellular
Classifier: Development Status :: 5 - Production/Stable
Classifier: Programming Language :: Python
Requires-Python: >=3.9
License-File: COPYING
Requires-Dist: gsm0338
Requires-Dist: construct>=2.9.51
Dynamic: license-file
